LICENSE
MANIFEST.in
README.rst
setup.cfg
setup.py
Flask_Genshi.egg-info/PKG-INFO
Flask_Genshi.egg-info/SOURCES.txt
Flask_Genshi.egg-info/dependency_links.txt
Flask_Genshi.egg-info/namespace_packages.txt
Flask_Genshi.egg-info/not-zip-safe
Flask_Genshi.egg-info/requires.txt
Flask_Genshi.egg-info/top_level.txt
docs/Makefile
docs/conf.py
docs/index.rst
docs/make.bat
docs/_static/flask-genshi.png
docs/_themes/.gitignore
docs/_themes/LICENSE
docs/_themes/README
docs/_themes/flask_theme_support.py
docs/_themes/.git/FETCH_HEAD
docs/_themes/.git/HEAD
docs/_themes/.git/config
docs/_themes/.git/description
docs/_themes/.git/index
docs/_themes/.git/packed-refs
docs/_themes/.git/hooks/applypatch-msg.sample
docs/_themes/.git/hooks/commit-msg.sample
docs/_themes/.git/hooks/post-commit.sample
docs/_themes/.git/hooks/post-receive.sample
docs/_themes/.git/hooks/post-update.sample
docs/_themes/.git/hooks/pre-applypatch.sample
docs/_themes/.git/hooks/pre-commit.sample
docs/_themes/.git/hooks/pre-rebase.sample
docs/_themes/.git/hooks/prepare-commit-msg.sample
docs/_themes/.git/hooks/update.sample
docs/_themes/.git/info/exclude
docs/_themes/.git/logs/HEAD
docs/_themes/.git/logs/refs/heads/master
docs/_themes/.git/objects/pack/pack-922dbfa09906cc02e20811d65b0b1b316f1156ea.idx
docs/_themes/.git/objects/pack/pack-922dbfa09906cc02e20811d65b0b1b316f1156ea.pack
docs/_themes/.git/refs/heads/master
docs/_themes/.git/refs/remotes/origin/HEAD
docs/_themes/flask/layout.html
docs/_themes/flask/relations.html
docs/_themes/flask/theme.conf
docs/_themes/flask/static/flasky.css_t
docs/_themes/flask/static/small_flask.css
docs/_themes/flask_small/layout.html
docs/_themes/flask_small/theme.conf
docs/_themes/flask_small/static/flasky.css_t
flaskext/__init__.py
flaskext/genshi.py
tests/__init__.py
tests/context_processors.py
tests/filters.py
tests/i18n.py
tests/jinja_tests_and_filters.py
tests/module_templates.py
tests/rendering.py
tests/signals.py
tests/strings.py
tests/utils.py
tests/flask_genshi_testapp/__init__.py
tests/flask_genshi_testapp/package_mod/__init__.py
tests/flask_genshi_testapp/package_mod/templates/module-template.txt
tests/flask_genshi_testapp/package_mod/templates/nonmodule-template.txt
tests/flask_genshi_testapp/templates/context.html
